ValidateurGenerique/FormValidator.py
ValidateurGenerique/SchemaValidator.py
ValidateurGenerique/Transformations.py
ValidateurGenerique/__init__.py
validateurgenerique-0.3.0.dist-info/LICENSE
validateurgenerique-0.3.0.dist-info/METADATA
validateurgenerique-0.3.0.dist-info/WHEEL
validateurgenerique-0.3.0.dist-info/top_level.txt
validateurgenerique-0.3.0.dist-info/RECORD
